joelsCalcPackage/__init__.py
joelsCalcPackage/add.py
joelsCalcPackage/subtract.py
joelsCalcPackage/extras/__init__.py
joelsCalcPackage/extras/divide.py
joelsCalcPackage/extras/multiply.py
matiCalpackage/__init__.py
matiCalpackage/add.py
matiCalpackage/subtract.py
matiCalpackage/extras/__init__.py
matiCalpackage/extras/divide.py
matiCalpackage/extras/multiply.py
joelsCalcPackage-0.0.1.dist-info/METADATA
joelsCalcPackage-0.0.1.dist-info/WHEEL
joelsCalcPackage-0.0.1.dist-info/top_level.txt
joelsCalcPackage-0.0.1.dist-info/RECORD
